{
  "depots": [
    {
      "name": "Seoul Main Depot",
      "index": 0,
      "coordinate": {
        "lng": 126.978,
        "lat": 37.5665
      }
    },
    {
      "name": "Gangnam Distribution Center",
      "index": 1,
      "coordinate": {
        "lng": 127.0276,
        "lat": 37.4979
      }
    }
  ],
  "daily_visits": [
    {
      "day_id": "2025-01-15",
      "visits": [
        {
          "name": "Hongdae Store",
          "index": null,
          "service_time": 15,
          "coordinate": {
            "lng": 126.927,
            "lat": 37.5563
          },
          "volume": 2.5,
          "weight": 25.0,
          "extra_demands": [
            3,
            1
          ],
          "unassigned_penalty": 1000.0,
          "time_window": [
            "2025-01-15T09:00:00",
            "2025-01-15T12:00:00"
          ],
          "early_delivery_required": false
        },
        {
          "name": "Itaewon Market",
          "index": null,
          "service_time": 20,
          "coordinate": {
            "lng": 126.9947,
            "lat": 37.5346
          },
          "volume": 1.8,
          "weight": 18.5,
          "extra_demands": [
            2,
            0
          ],
          "unassigned_penalty": 800.0,
          "time_window": [
            "2025-01-15T10:00:00",
            "2025-01-15T14:00:00"
          ],
          "early_delivery_required": true
        },
        {
          "name": "Myeongdong Shopping Center",
          "index": null,
          "service_time": 10,
          "coordinate": {
            "lng": 126.9849,
            "lat": 37.5636
          },
          "volume": 0.5,
          "weight": 8.2,
          "extra_demands": [
            1,
            2
          ],
          "unassigned_penalty": 500.0,
          "time_window": [
            "2025-01-15T13:00:00",
            "2025-01-15T17:00:00"
          ],
          "early_delivery_required": false
        }
      ],
      "delivery_start_time": "2025-01-15T08:00:00"
    },
    {
      "day_id": "2025-01-16",
      "visits": [
        {
          "name": "Gangnam Station Plaza",
          "index": null,
          "service_time": 25,
          "coordinate": {
            "lng": 127.0276,
            "lat": 37.4979
          },
          "volume": 3.2,
          "weight": 35.7,
          "extra_demands": [
            4,
            2
          ],
          "unassigned_penalty": 1200.0,
          "time_window": [
            "2025-01-16T09:30:00",
            "2025-01-16T13:00:00"
          ],
          "early_delivery_required": false
        },
        {
          "name": "Dongdaemun Fashion Town",
          "index": null,
          "service_time": 18,
          "coordinate": {
            "lng": 127.0089,
            "lat": 37.5658
          },
          "volume": 2.1,
          "weight": 22.3,
          "extra_demands": [
            2,
            3
          ],
          "unassigned_penalty": 900.0,
          "time_window": [
            "2025-01-16T11:00:00",
            "2025-01-16T15:00:00"
          ],
          "early_delivery_required": true
        }
      ],
      "delivery_start_time": "2025-01-16T08:30:00"
    }
  ],
  "vehicles": [
    {
      "name": "Truck-001",
      "volume_capacity": 15.0,
      "weight_capacity": 500.0,
      "extra_capacities": [
        20,
        10
      ],
      "work_start_time": "2025-01-15T07:00:00",
      "work_end_time": "2025-01-15T19:00:00",
      "vehicle_type": "car",
      "ownership_type": "owned",
      "start_depot_name": "Seoul Main Depot",
      "end_depot_name": "Seoul Main Depot",
      "fixed_cost_default": 5000.0,
      "fixed_cost_if_assigned": 2000.0,
      "fuel_cost_per_km": 150.0,
      "visit_preference": {
        "Hongdae Store": 2,
        "Itaewon Market": 1,
        "Myeongdong Shopping Center": 0
      },
      "first_visit_costs": {
        "Hongdae Store": 3000,
        "Itaewon Market": 2500,
        "Myeongdong Shopping Center": 2000
      },
      "consecutive_visit_tiered_costs": [
        [
          5000,
          1000
        ],
        [
          10000,
          1500
        ],
        [
          1000000000,
          3000
        ]
      ]
    },
    {
      "name": "Van-002",
      "volume_capacity": 8.0,
      "weight_capacity": 200.0,
      "extra_capacities": [
        15,
        5
      ],
      "work_start_time": "2025-01-15T08:00:00",
      "work_end_time": "2025-01-15T18:00:00",
      "vehicle_type": "car",
      "ownership_type": "rented",
      "start_depot_name": "Gangnam Distribution Center",
      "end_depot_name": "Gangnam Distribution Center",
      "fixed_cost_default": 3000.0,
      "fixed_cost_if_assigned": 1500.0,
      "fuel_cost_per_km": 120.0,
      "visit_preference": {
        "Gangnam Station Plaza": 3,
        "Dongdaemun Fashion Town": 1
      },
      "first_visit_costs": {
        "Gangnam Station Plaza": 2000,
        "Dongdaemun Fashion Town": 2200
      },
      "consecutive_visit_tiered_costs": [
        [
          3000,
          800
        ],
        [
          8000,
          1200
        ],
        [
          1000000000,
          2500
        ]
      ]
    },
    {
      "name": "Bike-003",
      "volume_capacity": 0.5,
      "weight_capacity": 15.0,
      "extra_capacities": [
        5,
        2
      ],
      "work_start_time": "2025-01-15T09:00:00",
      "work_end_time": "2025-01-15T17:00:00",
      "vehicle_type": "bike",
      "ownership_type": "owned",
      "start_depot_name": "Seoul Main Depot",
      "end_depot_name": "Seoul Main Depot",
      "fixed_cost_default": 1000.0,
      "fixed_cost_if_assigned": 500.0,
      "fuel_cost_per_km": 0.0,
      "visit_preference": {
        "Myeongdong Shopping Center": 2
      },
      "first_visit_costs": {
        "Myeongdong Shopping Center": 1000
      },
      "consecutive_visit_tiered_costs": [
        [
          2000,
          300
        ],
        [
          5000,
          500
        ],
        [
          1000000000,
          1000
        ]
      ]
    }
  ],
  "objective_costs": [
    "fixed_cost",
    "fuel_cost",
    "first_visit_cost",
    "consecutive_visit_tiered_cost"
  ],
  "option": {
    "timelimit": 5,
    "distance_type": "euclidean"
  }
}
